{"id": 28657, "title": "NASA Scientists Find New Human-Caused Shifts in Global Water Cycle", "authors": [], "url": "https://www.nasa.gov/missions/gpm/nasa-scientists-find-new-human-caused-shifts-in-global-water-cycle/", "image_url": "https://www.nasa.gov/wp-content/uploads/2025/01/deathvalleynps.jpeg", "news_site": "NASA", "summary": "In a recently published paper, NASA scientists use nearly 20 years of observations to show that the global water cycle is shifting in unprecedented ways. The majority of those shifts are driven by activities such as agriculture and could have impacts on ecosystems and water management, especially in certain regions. \u201cWe established with data assimilation [\u2026]", "published_at": "2025-01-16T16:27:13Z", "updated_at": "2025-01-16T16:30:10.960649Z", "featured": false, "launches": [], "events": []}